_manylinux.py
no_manylinux-3.0.0.dist-info/LICENSE
no_manylinux-3.0.0.dist-info/METADATA
no_manylinux-3.0.0.dist-info/WHEEL
no_manylinux-3.0.0.dist-info/top_level.txt
no_manylinux-3.0.0.dist-info/RECORD
